pytest_maxcov/__init__.py
pytest_maxcov/plugin.py
pytest_maxcov-1.0.0.dist-info/LICENSE
pytest_maxcov-1.0.0.dist-info/METADATA
pytest_maxcov-1.0.0.dist-info/WHEEL
pytest_maxcov-1.0.0.dist-info/entry_points.txt
pytest_maxcov-1.0.0.dist-info/RECORD
