Metadata-Version: 2.1
Name: pytest-maxcov
Version: 1.0.0
Summary: Compute the maximum coverage available through pytest with the minimum execution time cost
License: MIT
Author: Jon Connell
Author-email: python@figsandfudge.com
Requires-Python: >=3.8,<4.0
Classifier: Framework :: Pytest
Classifier: Intended Audience :: Developers
Classifier: License :: OSI Approved :: MIT License
Classifier: Operating System :: OS Independent
Classifier: Programming Language :: Python :: 3
Classifier: Programming Language :: Python :: 3.8
Classifier: Programming Language :: Python :: 3.9
Classifier: Programming Language :: Python :: 3.10
Classifier: Programming Language :: Python :: 3.11
Classifier: Programming Language :: Python :: 3
Classifier: Programming Language :: Python :: 3.10
Classifier: Programming Language :: Python :: 3.11
Classifier: Programming Language :: Python :: 3.8
Classifier: Programming Language :: Python :: 3.9
Requires-Dist: coverage (>=7.2.7,<8.0.0)
Requires-Dist: pytest (>=7.4.0,<8.0.0)
Requires-Dist: pytest-cov (>=4.1.0,<5.0.0)
Project-URL: Documentation, https://github.com/masaccio/pytest-maxcov/blob/main/README.md
